rockydb/__init__.py
rockydb/app.py
rockydb/collection.py
rockydb/encoding.py
rockydb/index.py
rockydb/rocky.py
rockydb/text.py
rockydb-0.2.10.dist-info/LICENSE.md
rockydb-0.2.10.dist-info/WHEEL
rockydb-0.2.10.dist-info/METADATA
rockydb-0.2.10.dist-info/RECORD
