Metadata-Version: 2.1
Name: rockydb
Version: 0.2.10
Summary: A NoSQL database.
Home-page: https://github.com/aaldulimi/RockyDB
License: Apache-2.0
Keywords: NoSQL,Database
Author: Ahmed
Requires-Python: >=3.8,<3.11
Classifier: Development Status :: 4 - Beta
Classifier: Intended Audience :: Developers
Classifier: License :: OSI Approved :: Apache Software License
Classifier: Programming Language :: Python :: 3
Classifier: Programming Language :: Python :: 3.0
Classifier: Programming Language :: Python :: 3.10
Classifier: Programming Language :: Python :: 3.8
Classifier: Programming Language :: Python :: 3.9
Classifier: Topic :: Database
Classifier: Topic :: Database :: Database Engines/Servers
Classifier: Topic :: Software Development :: Build Tools
Classifier: Topic :: Software Development :: Libraries :: Python Modules
Requires-Dist: fastapi (>=0.85.1,<0.86.0)
Requires-Dist: pytest (>=7.2.0,<8.0.0)
Requires-Dist: rocksdict (==0.3.2)
Requires-Dist: uvicorn (>=0.19.0,<0.20.0)
Project-URL: Documentation, https://rockydb.readthedocs.io/
Project-URL: Repository, https://github.com/aaldulimi/RockyDB
